autoeq_cli.py
pyproject.toml
autoeq/__init__.py
autoeq/__main__.py
autoeq/batch_processing.py
autoeq/compat.py
autoeq/constants.py
autoeq/csv.py
autoeq/frequency_response.py
autoeq/peq.py
autoeq/utils.py
dbtools/constants.py
dbtools/crawler.py
dbtools/create_webapp_data.py
dbtools/crinacle_crawler.py
dbtools/crinacle_crawler_base.py
dbtools/headphonecom_crawler.py
dbtools/hypethe_sonics_crawler.py
dbtools/image_graph_parser.py
dbtools/innerfidelity_crawler.py
dbtools/manufacturer_index.py
dbtools/name_index.py
dbtools/name_prompt.py
dbtools/oratory1990_crawler.py
dbtools/prompt_list_item.py
dbtools/prune_results.py
dbtools/rtings_crawler.py
dbtools/squig_crawler.py
dbtools/update_result_indexes.py
webapp/main.py
autoeq_py313-1.4.2.dist-info/METADATA
autoeq_py313-1.4.2.dist-info/WHEEL
autoeq_py313-1.4.2.dist-info/entry_points.txt
autoeq_py313-1.4.2.dist-info/licenses/LICENSE
autoeq_py313-1.4.2.dist-info/RECORD
