Metadata-Version: 2.4
Name: autoeq-py313
Version: 1.4.2
Summary: Automatic headphone equalizer config generator - Python 3.13/3.14 optimized with free-threaded support
Project-URL: Homepage, https://github.com/jaakkopasanen/AutoEq
Project-URL: Python 3.13.2 comfortable, https://github.com/115dkk/AutoEq-pip313
Author-email: "Original author: Jaakko Pasanen" <jaakko.o.pasanen@gmail.com>, "Python 3.13/3.14 optimized: 115dkk" <qjrzbasd@naver.com>
License-File: LICENSE
Classifier: License :: OSI Approved :: MIT License
Classifier: Operating System :: OS Independent
Classifier: Programming Language :: Python :: 3
Requires-Python: <3.15,>=3.13
Requires-Dist: matplotlib>=3.8.0
Requires-Dist: numpy>=1.26.0
Requires-Dist: pandas>=2.0.0
Requires-Dist: pillow>=10.1.0
Requires-Dist: pyyaml>=6.0.1
Requires-Dist: scipy>=1.12.0
Requires-Dist: soundfile>=0.12.1
Requires-Dist: tabulate>=0.9.0
Requires-Dist: tqdm>=4.66.1
